[
  {
    "nom_etud": "Iulius Caesar IV",
    "prenom_etud": "Caius",
    "promotion_etud": 2010,
    "mail_etude": "Jules.Caesar@rome.biz",
    "partage": true,
    "id_statut": 3,
    "id_formation": 11,
    "note_campus": 1,
    "note_formation": 4,
    "note_general": 5,
    "commentaire": "Erat ingens, tam realiter nan est.Te potest ludere virtualis machinis belli, quod olim me commonuit bonum"
  },

  {
    "nom_etud": "Prince",
    "prenom_etud": "Pennington",
    "promotion_etud": 2010,
    "mail_etude": "pennington.prince@email.biz",
    "partage": true,
    "id_statut": 3,
    "id_formation": 29,
    "note_campus": 1,
    "note_formation": 4,
    "note_general": 5,
    "commentaire": "Ca passe"
  },
  {
    "nom_etud": "Morrison",
    "prenom_etud": "Blankenship",
    "promotion_etud": 2010,
    "mail_etude": "blankenship.morrison@email.me",
    "partage": false,
    "id_statut": 4,
    "id_formation": 6,
    "note_campus": 2,
    "note_formation": 3,
    "note_general": 2,
    "commentaire": "Master génial !"
  },
  {
    "nom_etud": "Duran",
    "prenom_etud": "Lourdes",
    "promotion_etud": 2010,
    "mail_etude": "lourdes.duran@email.tv",
    "partage": true,
    "id_statut": 5,
    "id_formation": 16,
    "note_campus": 1,
    "note_formation": 2,
    "note_general": 3,
    "commentaire": "A éviter"
  },
  {
    "nom_etud": "Barr",
    "prenom_etud": "Josie",
    "promotion_etud": 2010,
    "mail_etude": "josie.barr@email.us",
    "partage": true,
    "id_statut": 1,
    "id_formation": 23,
    "note_campus": 3,
    "note_formation": 5,
    "note_general": 2,
    "commentaire": "Master génial !"
  },
  {
    "nom_etud": "Vincent",
    "prenom_etud": "Joan",
    "promotion_etud": 2016,
    "mail_etude": "joan.vincent@email.co.uk",
    "partage": false,
    "id_statut": 4,
    "id_formation": 16,
    "note_campus": 5,
    "note_formation": 4,
    "note_general": 3,
    "commentaire": "Master génial !"
  },
  {
    "nom_etud": "Avery",
    "prenom_etud": "Clare",
    "promotion_etud": 2015,
    "mail_etude": "clare.avery@email.info",
    "partage": false,
    "id_statut": 5,
    "id_formation": 21,
    "note_campus": 4,
    "note_formation": 5,
    "note_general": 3,
    "commentaire": "Un très bon master"
  },
  {
    "nom_etud": "Franklin",
    "prenom_etud": "Mitzi",
    "promotion_etud": 2013,
    "mail_etude": "mitzi.franklin@email.org",
    "partage": true,
    "id_statut": 3,
    "id_formation": 26,
    "note_campus": 4,
    "note_formation": 5,
    "note_general": 1,
    "commentaire": "Dommage..."
  },
  {
    "nom_etud": "Webb",
    "prenom_etud": "Bartlett",
    "promotion_etud": 2012,
    "mail_etude": "bartlett.webb@email.com",
    "partage": false,
    "id_statut": 5,
    "id_formation": 26,
    "note_campus": 1,
    "note_formation": 1,
    "note_general": 4,
    "commentaire": "A éviter"
  },
  {
    "nom_etud": "Wong",
    "prenom_etud": "Elvira",
    "promotion_etud": 2009,
    "mail_etude": "elvira.wong@email.biz",
    "partage": false,
    "id_statut": 2,
    "id_formation": 31,
    "note_campus": 3,
    "note_formation": 4,
    "note_general": 2,
    "commentaire": "Ca passe"
  },
  {
    "nom_etud": "Farley",
    "prenom_etud": "Webster",
    "promotion_etud": 2011,
    "mail_etude": "webster.farley@email.name",
    "partage": true,
    "id_statut": 5,
    "id_formation": 12,
    "note_campus": 3,
    "note_formation": 1,
    "note_general": 5,
    "commentaire": "Ca passe"
  },
  {
    "nom_etud": "Fox",
    "prenom_etud": "Erickson",
    "promotion_etud": 2009,
    "mail_etude": "erickson.fox@email.ca",
    "partage": true,
    "id_statut": 2,
    "id_formation": 13,
    "note_campus": 2,
    "note_formation": 1,
    "note_general": 4,
    "commentaire": "Dommage..."
  },
  {
    "nom_etud": "Figueroa",
    "prenom_etud": "Madelyn",
    "promotion_etud": 2010,
    "mail_etude": "madelyn.figueroa@email.net",
    "partage": true,
    "id_statut": 3,
    "id_formation": 19,
    "note_campus": 2,
    "note_formation": 1,
    "note_general": 2,
    "commentaire": "Ca passe"
  },
  {
    "nom_etud": "Schroeder",
    "prenom_etud": "Jaclyn",
    "promotion_etud": 2011,
    "mail_etude": "jaclyn.schroeder@email.biz",
    "partage": false,
    "id_statut": 4,
    "id_formation": 4,
    "note_campus": 1,
    "note_formation": 5,
    "note_general": 4,
    "commentaire": "Ca passe"
  },
  {
    "nom_etud": "Brown",
    "prenom_etud": "Roslyn",
    "promotion_etud": 2009,
    "mail_etude": "roslyn.brown@email.me",
    "partage": true,
    "id_statut": 4,
    "id_formation": 18,
    "note_campus": 2,
    "note_formation": 5,
    "note_general": 5,
    "commentaire": "Master génial !"
  },
  {
    "nom_etud": "Townsend",
    "prenom_etud": "Kristy",
    "promotion_etud": 2008,
    "mail_etude": "kristy.townsend@email.tv",
    "partage": true,
    "id_statut": 1,
    "id_formation": 29,
    "note_campus": 3,
    "note_formation": 5,
    "note_general": 2,
    "commentaire": "A éviter"
  },
  {
    "nom_etud": "Gallegos",
    "prenom_etud": "Michael",
    "promotion_etud": 2009,
    "mail_etude": "michael.gallegos@email.us",
    "partage": false,
    "id_statut": 1,
    "id_formation": 24,
    "note_campus": 5,
    "note_formation": 5,
    "note_general": 1,
    "commentaire": "Master génial !"
  },
  {
    "nom_etud": "Cherry",
    "prenom_etud": "Cindy",
    "promotion_etud": 2018,
    "mail_etude": "cindy.cherry@email.co.uk",
    "partage": false,
    "id_statut": 3,
    "id_formation": 6,
    "note_campus": 5,
    "note_formation": 1,
    "note_general": 3,
    "commentaire": "Dommage..."
  },
  {
    "nom_etud": "Dean",
    "prenom_etud": "Nikki",
    "promotion_etud": 2011,
    "mail_etude": "nikki.dean@email.info",
    "partage": true,
    "id_statut": 2,
    "id_formation": 8,
    "note_campus": 3,
    "note_formation": 1,
    "note_general": 4,
    "commentaire": "Master génial !"
  },
  {
    "nom_etud": "Curry",
    "prenom_etud": "Dawn",
    "promotion_etud": 2010,
    "mail_etude": "dawn.curry@email.org",
    "partage": false,
    "id_statut": 1,
    "id_formation": 7,
    "note_campus": 2,
    "note_formation": 5,
    "note_general": 1,
    "commentaire": "Master génial !"
  },
  {
    "nom_etud": "Noel",
    "prenom_etud": "Waters",
    "promotion_etud": 2015,
    "mail_etude": "waters.noel@email.com",
    "partage": false,
    "id_statut": 5,
    "id_formation": 19,
    "note_campus": 2,
    "note_formation": 2,
    "note_general": 1,
    "commentaire": "Un très bon master"
  },
  {
    "nom_etud": "Collins",
    "prenom_etud": "Myra",
    "promotion_etud": 2016,
    "mail_etude": "myra.collins@email.biz",
    "partage": false,
    "id_statut": 1,
    "id_formation": 1,
    "note_campus": 5,
    "note_formation": 1,
    "note_general": 4,
    "commentaire": "Master génial !"
  },
  {
    "nom_etud": "Norris",
    "prenom_etud": "Letha",
    "promotion_etud": 2011,
    "mail_etude": "letha.norris@email.name",
    "partage": true,
    "id_statut": 4,
    "id_formation": 28,
    "note_campus": 4,
    "note_formation": 2,
    "note_general": 2,
    "commentaire": "Ca passe"
  },
  {
    "nom_etud": "Ray",
    "prenom_etud": "Valeria",
    "promotion_etud": 2017,
    "mail_etude": "valeria.ray@email.ca",
    "partage": true,
    "id_statut": 4,
    "id_formation": 8,
    "note_campus": 5,
    "note_formation": 4,
    "note_general": 1,
    "commentaire": "A éviter"
  },
  {
    "nom_etud": "Snyder",
    "prenom_etud": "Wanda",
    "promotion_etud": 2014,
    "mail_etude": "wanda.snyder@email.net",
    "partage": false,
    "id_statut": 1,
    "id_formation": 29,
    "note_campus": 2,
    "note_formation": 4,
    "note_general": 1,
    "commentaire": "Un très bon master"
  },
  {
    "nom_etud": "Burt",
    "prenom_etud": "Alisa",
    "promotion_etud": 2010,
    "mail_etude": "alisa.burt@email.biz",
    "partage": true,
    "id_statut": 2,
    "id_formation": 27,
    "note_campus": 2,
    "note_formation": 1,
    "note_general": 1,
    "commentaire": "Un très bon master"
  },
  {
    "nom_etud": "Mason",
    "prenom_etud": "Liliana",
    "promotion_etud": 2012,
    "mail_etude": "liliana.mason@email.me",
    "partage": true,
    "id_statut": 2,
    "id_formation": 2,
    "note_campus": 4,
    "note_formation": 3,
    "note_general": 1,
    "commentaire": "Ca passe"
  },
  {
    "nom_etud": "Jordan",
    "prenom_etud": "Barton",
    "promotion_etud": 2010,
    "mail_etude": "barton.jordan@email.tv",
    "partage": true,
    "id_statut": 5,
    "id_formation": 12,
    "note_campus": 1,
    "note_formation": 1,
    "note_general": 2,
    "commentaire": "Master génial !"
  },
  {
    "nom_etud": "Floyd",
    "prenom_etud": "Mayra",
    "promotion_etud": 2016,
    "mail_etude": "mayra.floyd@email.us",
    "partage": false,
    "id_statut": 2,
    "id_formation": 11,
    "note_campus": 3,
    "note_formation": 3,
    "note_general": 3,
    "commentaire": "Master génial !"
  },
  {
    "nom_etud": "Wise",
    "prenom_etud": "Melinda",
    "promotion_etud": 2018,
    "mail_etude": "melinda.wise@email.co.uk",
    "partage": true,
    "id_statut": 2,
    "id_formation": 8,
    "note_campus": 1,
    "note_formation": 2,
    "note_general": 3,
    "commentaire": "Master génial !"
  },
  {
    "nom_etud": "Barlow",
    "prenom_etud": "Mullins",
    "promotion_etud": 2017,
    "mail_etude": "mullins.barlow@email.info",
    "partage": false,
    "id_statut": 1,
    "id_formation": 2,
    "note_campus": 4,
    "note_formation": 4,
    "note_general": 3,
    "commentaire": "Master génial !"
  },
  {
    "nom_etud": "Travis",
    "prenom_etud": "Mills",
    "promotion_etud": 2009,
    "mail_etude": "mills.travis@email.org",
    "partage": true,
    "id_statut": 3,
    "id_formation": 19,
    "note_campus": 3,
    "note_formation": 2,
    "note_general": 1,
    "commentaire": "Ca passe"
  },
  {
    "nom_etud": "Carver",
    "prenom_etud": "Maricela",
    "promotion_etud": 2018,
    "mail_etude": "maricela.carver@email.com",
    "partage": true,
    "id_statut": 5,
    "id_formation": 1,
    "note_campus": 4,
    "note_formation": 1,
    "note_general": 4,
    "commentaire": "Dommage..."
  },
  {
    "nom_etud": "Talley",
    "prenom_etud": "Lori",
    "promotion_etud": 2017,
    "mail_etude": "lori.talley@email.biz",
    "partage": false,
    "id_statut": 1,
    "id_formation": 4,
    "note_campus": 2,
    "note_formation": 2,
    "note_general": 3,
    "commentaire": "A éviter"
  },
  {
    "nom_etud": "James",
    "prenom_etud": "Lillie",
    "promotion_etud": 2008,
    "mail_etude": "lillie.james@email.name",
    "partage": true,
    "id_statut": 1,
    "id_formation": 20,
    "note_campus": 3,
    "note_formation": 5,
    "note_general": 5,
    "commentaire": "A éviter"
  },
  {
    "nom_etud": "Chambers",
    "prenom_etud": "Spears",
    "promotion_etud": 2018,
    "mail_etude": "spears.chambers@email.ca",
    "partage": false,
    "id_statut": 1,
    "id_formation": 25,
    "note_campus": 1,
    "note_formation": 5,
    "note_general": 3,
    "commentaire": "A éviter"
  },
  {
    "nom_etud": "Bryant",
    "prenom_etud": "Clemons",
    "promotion_etud": 2018,
    "mail_etude": "clemons.bryant@email.net",
    "partage": true,
    "id_statut": 5,
    "id_formation": 17,
    "note_campus": 1,
    "note_formation": 1,
    "note_general": 4,
    "commentaire": "Master génial !"
  },
  {
    "nom_etud": "Summers",
    "prenom_etud": "Tate",
    "promotion_etud": 2012,
    "mail_etude": "tate.summers@email.biz",
    "partage": true,
    "id_statut": 1,
    "id_formation": 18,
    "note_campus": 2,
    "note_formation": 3,
    "note_general": 4,
    "commentaire": "Un très bon master"
  },
  {
    "nom_etud": "Forbes",
    "prenom_etud": "Margo",
    "promotion_etud": 2015,
    "mail_etude": "margo.forbes@email.me",
    "partage": false,
    "id_statut": 3,
    "id_formation": 26,
    "note_campus": 5,
    "note_formation": 5,
    "note_general": 4,
    "commentaire": "Master génial !"
  },
  {
    "nom_etud": "Nieves",
    "prenom_etud": "Mckinney",
    "promotion_etud": 2009,
    "mail_etude": "mckinney.nieves@email.tv",
    "partage": true,
    "id_statut": 1,
    "id_formation": 27,
    "note_campus": 1,
    "note_formation": 1,
    "note_general": 1,
    "commentaire": "Master génial !"
  },
  {
    "nom_etud": "Castaneda",
    "prenom_etud": "Marguerite",
    "promotion_etud": 2018,
    "mail_etude": "marguerite.castaneda@email.us",
    "partage": false,
    "id_statut": 5,
    "id_formation": 20,
    "note_campus": 1,
    "note_formation": 4,
    "note_general": 1,
    "commentaire": "A éviter"
  },
  {
    "nom_etud": "Jackson",
    "prenom_etud": "Chrystal",
    "promotion_etud": 2015,
    "mail_etude": "chrystal.jackson@email.co.uk",
    "partage": false,
    "id_statut": 5,
    "id_formation": 1,
    "note_campus": 3,
    "note_formation": 5,
    "note_general": 2,
    "commentaire": "Dommage..."
  },
  {
    "nom_etud": "Mcgee",
    "prenom_etud": "Aimee",
    "promotion_etud": 2017,
    "mail_etude": "aimee.mcgee@email.info",
    "partage": true,
    "id_statut": 1,
    "id_formation": 4,
    "note_campus": 5,
    "note_formation": 1,
    "note_general": 3,
    "commentaire": "A éviter"
  },
  {
    "nom_etud": "Fischer",
    "prenom_etud": "Howe",
    "promotion_etud": 2009,
    "mail_etude": "howe.fischer@email.org",
    "partage": false,
    "id_statut": 4,
    "id_formation": 20,
    "note_campus": 5,
    "note_formation": 3,
    "note_general": 5,
    "commentaire": "A éviter"
  },
  {
    "nom_etud": "Luna",
    "prenom_etud": "Georgia",
    "promotion_etud": 2008,
    "mail_etude": "georgia.luna@email.com",
    "partage": false,
    "id_statut": 4,
    "id_formation": 5,
    "note_campus": 1,
    "note_formation": 5,
    "note_general": 1,
    "commentaire": "Master génial !"
  },
  {
    "nom_etud": "Tran",
    "prenom_etud": "Ofelia",
    "promotion_etud": 2017,
    "mail_etude": "ofelia.tran@email.biz",
    "partage": true,
    "id_statut": 5,
    "id_formation": 22,
    "note_campus": 2,
    "note_formation": 2,
    "note_general": 5,
    "commentaire": "Dommage..."
  },
  {
    "nom_etud": "Monroe",
    "prenom_etud": "Conway",
    "promotion_etud": 2013,
    "mail_etude": "conway.monroe@email.name",
    "partage": true,
    "id_statut": 3,
    "id_formation": 26,
    "note_campus": 3,
    "note_formation": 2,
    "note_general": 2,
    "commentaire": "A éviter"
  },
  {
    "nom_etud": "Burke",
    "prenom_etud": "Shannon",
    "promotion_etud": 2013,
    "mail_etude": "shannon.burke@email.ca",
    "partage": false,
    "id_statut": 2,
    "id_formation": 31,
    "note_campus": 2,
    "note_formation": 4,
    "note_general": 1,
    "commentaire": "Master génial !"
  },
  {
    "nom_etud": "Hughes",
    "prenom_etud": "Richards",
    "promotion_etud": 2009,
    "mail_etude": "richards.hughes@email.net",
    "partage": false,
    "id_statut": 4,
    "id_formation": 8,
    "note_campus": 4,
    "note_formation": 1,
    "note_general": 2,
    "commentaire": "A éviter"
  },
  {
    "nom_etud": "Barber",
    "prenom_etud": "Neal",
    "promotion_etud": 2017,
    "mail_etude": "neal.barber@email.biz",
    "partage": false,
    "id_statut": 3,
    "id_formation": 22,
    "note_campus": 3,
    "note_formation": 4,
    "note_general": 2,
    "commentaire": "Un très bon master"
  },
  {
    "nom_etud": "Rivers",
    "prenom_etud": "Kane",
    "promotion_etud": 2013,
    "mail_etude": "kane.rivers@email.me",
    "partage": true,
    "id_statut": 5,
    "id_formation": 6,
    "note_campus": 2,
    "note_formation": 1,
    "note_general": 5,
    "commentaire": "Master génial !"
  },
  {
    "nom_etud": "Poole",
    "prenom_etud": "Shanna",
    "promotion_etud": 2012,
    "mail_etude": "shanna.poole@email.tv",
    "partage": false,
    "id_statut": 4,
    "id_formation": 5,
    "note_campus": 2,
    "note_formation": 2,
    "note_general": 4,
    "commentaire": "A éviter"
  },
  {
    "nom_etud": "Calderon",
    "prenom_etud": "Meredith",
    "promotion_etud": 2012,
    "mail_etude": "meredith.calderon@email.us",
    "partage": true,
    "id_statut": 4,
    "id_formation": 22,
    "note_campus": 4,
    "note_formation": 3,
    "note_general": 5,
    "commentaire": "A éviter"
  },
  {
    "nom_etud": "Wade",
    "prenom_etud": "Cabrera",
    "promotion_etud": 2018,
    "mail_etude": "cabrera.wade@email.co.uk",
    "partage": true,
    "id_statut": 1,
    "id_formation": 28,
    "note_campus": 1,
    "note_formation": 1,
    "note_general": 4,
    "commentaire": "Master génial !"
  },
  {
    "nom_etud": "Dodson",
    "prenom_etud": "Noemi",
    "promotion_etud": 2009,
    "mail_etude": "noemi.dodson@email.info",
    "partage": false,
    "id_statut": 2,
    "id_formation": 27,
    "note_campus": 4,
    "note_formation": 1,
    "note_general": 2,
    "commentaire": "A éviter"
  },
  {
    "nom_etud": "Keith",
    "prenom_etud": "Estella",
    "promotion_etud": 2015,
    "mail_etude": "estella.keith@email.org",
    "partage": false,
    "id_statut": 3,
    "id_formation": 6,
    "note_campus": 2,
    "note_formation": 4,
    "note_general": 2,
    "commentaire": "Master génial !"
  },
  {
    "nom_etud": "Patterson",
    "prenom_etud": "Gibbs",
    "promotion_etud": 2008,
    "mail_etude": "gibbs.patterson@email.com",
    "partage": true,
    "id_statut": 1,
    "id_formation": 13,
    "note_campus": 5,
    "note_formation": 2,
    "note_general": 2,
    "commentaire": "Ca passe"
  },
  {
    "nom_etud": "Santiago",
    "prenom_etud": "Keller",
    "promotion_etud": 2013,
    "mail_etude": "keller.santiago@email.biz",
    "partage": false,
    "id_statut": 3,
    "id_formation": 29,
    "note_campus": 2,
    "note_formation": 2,
    "note_general": 2,
    "commentaire": "Ca passe"
  },
  {
    "nom_etud": "Bridges",
    "prenom_etud": "Esmeralda",
    "promotion_etud": 2013,
    "mail_etude": "esmeralda.bridges@email.name",
    "partage": false,
    "id_statut": 4,
    "id_formation": 12,
    "note_campus": 5,
    "note_formation": 4,
    "note_general": 2,
    "commentaire": "Ca passe"
  }
]